{
  "manual": [
    {
      "section": "Comenzando",
      "topics": [
        "Clases sociales",
        "Habilidades",
        "Controles",
        "Razas y atributos",
        "Crear un personaje",
        "Comandos"
      ]
    },
    {
      "section": "Lo Basico",
      "topics": [
        "Vida y muerte",
        "Comida y bebida",
        "Un jugador con honor",
        "Leyes",
        "Subir de nivel",
        "Centinela",
        "Skills",
        "Supervivencia"
      ]
    },
    {
      "section": "Dinero",
      "topics": ["Introduccion", "Comercio", "Comercio seguro", "Bancos"]
    },
    {
      "section": "Profesiones",
      "topics": ["Talador", "Pescador", "Herrero", "Minero", "Carpintero"]
    },
    {
      "section": "Equipamiento",
      "topics": [
        "Vestimentas",
        "Armaduras",
        "Pociones",
        "Armas",
        "Tunicas",
        "Cascos y escudos",
        "Items magicos",
        "Magias"
      ]
    },
    {
      "section": "Entrenamiento",
      "topics": ["Criaturas hostiles", "Party", "Domar animales"]
    },
    {
      "section": "Facciones",
      "topics": ["Armada Real", "Legion Oscura"]
    },
    {
      "section": "Mundo",
      "topics": ["Ciudades", "Dungeons", "Mapa"]
    },
    {
      "section": "Avanzado",
      "topics": ["Clanes", "Navegacion", "Comandos", "Retos"]
    }
  ],
  "placeholder": "Bienvenido, aventurero, a las maravillosas Tierras de Arcanus Online. Si buscas riqueza, aventuras, amigos, enemigos, tierras por conquistar o criaturas por matar, estás en el lugar indicado porque aquí las emociones no te harán esperar. Tenemos dos caminos a seguir en estas conflictivas tierras: el camino del bien o el tétrico camino del mal. No importa cuál decidas seguir, no te arrepentirás, y si lo haces, será demasiado tarde. Te invito a adentrarte en estas tierras, y si el destino lo desea, formar parte de esta historia que se escribe día a día. ¡Mucha suerte en tu aventura!"
}
